nbdevAuto/__init__.py
nbdevAuto/_modidx.py
nbdevAuto/automate.py
nbdevAuto/core.py
nbdevAuto/functions.py
nbdevAuto/pdf.py
nbdevAuto-0.3.26.dist-info/LICENSE
nbdevAuto-0.3.26.dist-info/METADATA
nbdevAuto-0.3.26.dist-info/WHEEL
nbdevAuto-0.3.26.dist-info/entry_points.txt
nbdevAuto-0.3.26.dist-info/top_level.txt
nbdevAuto-0.3.26.dist-info/RECORD
