Metadata-Version: 2.1
Name: nbdevAuto
Version: 0.3.26
Summary: automating nbdev
Home-page: https://github.com/bthek1/nbdevAuto
Author: Benedict Thekkel
Author-email: bthekkel1@gmail.com
License: Apache Software License 2.0
Keywords: nbdev jupyter notebook python
Classifier: Development Status :: 4 - Beta
Classifier: Intended Audience :: Developers
Classifier: Natural Language :: English
Classifier: Programming Language :: Python :: 3.7
Classifier: Programming Language :: Python :: 3.8
Classifier: Programming Language :: Python :: 3.9
Classifier: Programming Language :: Python :: 3.10
Classifier: License :: OSI Approved :: Apache Software License
Requires-Python: >=3.7
License-File: LICENSE
Requires-Dist: graphviz
Provides-Extra: dev
